LabExers/FinalExam Final/ProblemD/ProblemD.v

module ProblemD (
    input  wire       clk,        // posedge clock
    input  wire       reset,      // active-high async reset
    input  wire [1:0] A,          // control: 00 even seq, 01 odd seq, 10 load 15, 11 hold
    output reg  [3:0] Z           // current count
);

    reg [3:0] next_Z;

    // Next-state logic enforces the requested sequences
    always @(*) begin
        next_Z = Z; // default hold
        case (A)
            2'b00: begin
                if (Z[0] == 1'b1)
                    next_Z = 4'd0;          // if coming from odd path, restart even sequence
                else
                    next_Z = Z + 4'd2;      // 0,2,4,...,14 cycling via modulo-16
            end
            2'b01: begin
                if (Z[0] == 1'b0)
                    next_Z = 4'd1;          // force odd start when switching from even path
                else
                    next_Z = Z + 4'd2;      // 1,3,5,...,15 then wraps to 1
            end
            2'b10: next_Z = 4'd15;          // immediate load to 15
            default: next_Z = Z;            // hold for 2'b11 or any unused codes
        endcase
    end

    always @(posedge clk or posedge reset) begin
        if (reset)
            Z <= 4'd0;
        else
            Z <= next_Z;
    end

endmodule

LabExers/FinalExam Final/ProblemD/tb_ProblemD.v
`timescale 1ns / 1ps

module tb_ProblemD;

    // Inputs to DUT (Device Under Test)
    reg clk;
    reg reset;
    reg [1:0] A;

    // Outputs from DUT
    wire [3:0] Z;

    // Instantiate the Device Under Test (DUT)
    ProblemD uut (
        .clk(clk), 
        .reset(reset), 
        .A(A), 
        .Z(Z)
    );

    // Clock generation: 10ns period (100MHz)
    initial begin
        clk = 0;
        forever #5 clk = ~clk;
    end

    // Test Sequence
    initial begin

        // Initialize Inputs
        reset = 1;
        A = 2'b11; // Hold mode initially
        
        // Wait 20ns and release reset
        #20;
        reset = 0;
        $display("--- Simulation Start ---");

        // -------------------------------------------------
        // TEST CASE 1: Test Even Sequence (A = 00)
        // -------------------------------------------------
        // Expect: 0 -> 2 -> 4 -> ... -> 14 -> 0
        $display("[Time %0t] Testing Even Sequence (A=00)", $time);
        A = 2'b00;
        #80; // Wait 8 clock cycles to see the count progress

        // -------------------------------------------------
        // TEST CASE 2: Test Hold (A = 11)
        // -------------------------------------------------
        // Expect: Z should stop changing
        $display("[Time %0t] Testing Hold (A=11) - Current Z: %d", $time, Z);
        A = 2'b11;
        #30; 

        // -------------------------------------------------
        // TEST CASE 3: Test Load 15 (A = 10)
        // -------------------------------------------------
        // Expect: Z becomes 15 immediately on next clock
        $display("[Time %0t] Testing Load 15 (A=10)", $time);
        A = 2'b10;
        #10; // Wait 1 clock cycle

        // -------------------------------------------------
        // TEST CASE 4: Test Odd Sequence (A = 01)
        // -------------------------------------------------
        // Expect: 15 (current) -> 1 -> 3 -> 5...
        // Note: Your logic says if Z is odd, next is Z+2. 
        // Since 15 is odd, it should wrap to 1 (15+2 = 17 = 1 mod 16)
        $display("[Time %0t] Testing Odd Sequence (A=01) from 15", $time);
        A = 2'b01;
        #80; // Let it count for a while

        // -------------------------------------------------
        // TEST CASE 5: Test Transition Logic (Odd -> Even)
        // -------------------------------------------------
        // Currently Z is likely odd. Switching to A=00.
        // Logic: if (Z[0]==1) next_Z = 0.
        $display("[Time %0t] Testing Switch: Odd Z to Even Mode (A=00)", $time);
        A = 2'b00;
        #20; // Should reset to 0 then count 2, 4...

        // -------------------------------------------------
        // TEST CASE 6: Test Transition Logic (Even -> Odd)
        // -------------------------------------------------
        // Currently Z is Even. Switching to A=01.
        // Logic: if (Z[0]==0) next_Z = 1.
        $display("[Time %0t] Testing Switch: Even Z to Odd Mode (A=01)", $time);
        A = 2'b01;
        #20; // Should jump to 1 then count 3, 5...

        // -------------------------------------------------
        // TEST CASE 7: Test Asynchronous Reset
        // -------------------------------------------------
        $display("[Time %0t] Testing Async Reset", $time);
        #3 reset = 1; // Assert reset not on clock edge to prove async nature
        #10 reset = 0;

        $display("--- Simulation End ---");
        $stop;
    end

    // Monitor changes to console
    initial begin
        $monitor("Time=%0t | Reset=%b A=%b | Z=%d (binary %b)", 
                 $time, reset, A, Z, Z);
    end

endmodule

LabExers/FinalExam Final/ProblemD/simulation/modelsim/waveform.vcd
$date
	Wed Dec 17 23:27:52 2025
$end
$version
	ModelSim Version 2020.1
$end
$timescale
	1ps
$end

$scope module tb_ProblemD $end
$var reg 1 ! clk $end
$var reg 1 " reset $end
$var reg 2 # A [1:0] $end
$var wire 1 $ Z [3] $end
$var wire 1 % Z [2] $end
$var wire 1 & Z [1] $end
$var wire 1 ' Z [0] $end

$scope module uut $end
$var wire 1 ( clk $end
$var wire 1 ) reset $end
$var wire 1 * A [1] $end
$var wire 1 + A [0] $end
$var reg 4 , Z [3:0] $end
$var reg 4 - next_Z [3:0] $end
$upscope $end
$upscope $end
$enddefinitions $end
#0
$dumpvars
0!
1"
b11 #
b0 ,
b0 -
0'
0&
0%
0$
1+
1*
1)
0(
$end
#5000
1!
1(
#10000
0!
0(
#15000
1!
1(
#20000
0"
b0 #
0!
0)
0+
0*
0(
b10 -
#25000
1!
1(
b10 ,
1&
b100 -
#30000
0!
0(
#35000
1!
1(
b100 ,
0&
1%
b110 -
#40000
0!
0(
#45000
1!
1(
b110 ,
1&
b1000 -
#50000
0!
0(
#55000
1!
1(
b1000 ,
0&
0%
1$
b1010 -
#60000
0!
0(
#65000
1!
1(
b1010 ,
1&
b1100 -
#70000
0!
0(
#75000
1!
1(
b1100 ,
0&
1%
b1110 -
#80000
0!
0(
#85000
1!
1(
b1110 ,
1&
b0 -
#90000
0!
0(
#95000
1!
1(
b0 ,
0&
0%
0$
b10 -
#100000
b11 #
0!
1+
1*
0(
b0 -
#105000
1!
1(
#110000
0!
0(
#115000
1!
1(
#120000
0!
0(
#125000
1!
1(
#130000
b10 #
0!
0+
0(
b1111 -
#135000
1!
1(
b1111 ,
1'
1&
1%
1$
#140000
b1 #
0!
1+
0*
0(
b1 -
#145000
1!
1(
b1 ,
0&
0%
0$
b11 -
#150000
0!
0(
#155000
1!
1(
b11 ,
1&
b101 -
#160000
0!
0(
#165000
1!
1(
b101 ,
0&
1%
b111 -
#170000
0!
0(
#175000
1!
1(
b111 ,
1&
b1001 -
#180000
0!
0(
#185000
1!
1(
b1001 ,
0&
0%
1$
b1011 -
#190000
0!
0(
#195000
1!
1(
b1011 ,
1&
b1101 -
#200000
0!
0(
#205000
1!
1(
b1101 ,
0&
1%
b1111 -
#210000
0!
0(
#215000
1!
1(
b1111 ,
1&
b1 -
#220000
b0 #
0!
0+
0(
b1111 -
b0 -
#225000
1!
1(
b0 ,
0'
0&
0%
0$
b10 -
#230000
0!
0(
#235000
1!
1(
b10 ,
1&
b100 -
#240000
b1 #
0!
1+
0(
b10 -
b1 -
#245000
1!
1(
b1 ,
1'
0&
b11 -
#250000
0!
0(
#255000
1!
1(
b11 ,
1&
b101 -
#260000
0!
0(
#263000
1"
1)
b0 ,
0'
0&
b0 -
b1 -
#265000
1!
1(
#270000
0!
0(
#273000
0"
